{"System": {"system_id": 10180, "site_id": 3670, "public_name": "Pvoutput.org Hideaway Power Plant", "area": "", "power": "10.0", "started_on": "2014-04-13 00:00:00", "ended_on": "", "comments": "PVOUTPUT_ID=19310", "data_prize": "f", "timezone_code": "America/New_York", "us_region": "Unknown"}, "Site": {"site_id": "3670", "name": "Pvoutput.org 19310 Hideaway Power Plant", "public_name": "Pvoutput.org Hideaway Power Plant", "location": "ZIP: 33755", "us_region": "Unknown", "latitude": "27.979114", "longitude": "-82.78166", "elevation": "0.0", "climate_type": "Cfa"}, "Mount": {"Mount 0": {"mount_id": 12937, "name": "Pvoutput.org 19310 Hideaway Power Plant_mount", "manufacturer": "Unknown", "model": "Unknown", "tracking": "f", "type": "unknown", "azimuth": "180.0", "tilt": "18.5"}}, "Inverters": {"Inverter 0": {"inverter_id": "16601", "name": "Pvoutput.org 19310 Hideaway Power Plant_inverter", "manufacturer": "Enphase M215", "model": "Enphase M215", "type": "Unknown", "quantity": "40", "serial_num": "Unknown", "comments": "", "time_interval": "L", "modules_per_string": "", "num_strings": ""}}, "Modules": {"Module 0": {"module_id": "13194", "inverter_id": "None", "name": "Pvoutput.org 19310 Hideaway Power Plant_module", "manufacturer": "Axitec 250", "model": "Axitec 250", "type": "Unknown", "quantity": "40", "start_on": "2014-04-13 00:00:00", "end_on": "", "serial_num": "Unknown", "reference_module": "False", "comments": "PVOUTPUT_ID=19310"}}, "Meters": {}, "Other Instruments": {}, "Metrics": {"ac_energy_inv_16601": {"metric_id": 87996, "sensor_name": "ac_energy_kwh", "common_name": "AC energy cumulative", "raw_units": "Wh", "units": "kWh", "calc_scale": 0.001, "calc_offset": 0.0, "calc_details": null, "aggregation_type": "avg", "source_type": "INVERTER", "source_id": 16601, "comments": null, "offline": false}, "ac_power_inv_16601": {"metric_id": 87997, "sensor_name": "ac_power_W", "common_name": "AC power", "raw_units": "W", "units": "kW", "calc_scale": 0.001, "calc_offset": 0.0, "calc_details": null, "aggregation_type": "avg", "source_type": "INVERTER", "source_id": 16601, "comments": null, "offline": false}}}