{"System": {"system_id": 14504, "site_id": 7259, "name": "0022F2002DCE", "public_name": "PVDB_0022F2002DCE", "area": "", "power": "13.49", "started_on": "2013-12-31 00:00:00", "ended_on": "", "comments": "PVDB_SYSTEM_ID=0022F2002DCE", "public": "t", "access_id": 18, "grouping": "PVDB", "data_prize": "f", "timezone_code": "America/Los_Angeles"}, "Site": {"site_id": "7259", "name": "0022F2002DCE", "public_name": "PVDB_0022F2002DCE", "latitude": "33.76374", "longitude": "-117.79618", "elevation": "74.1800231933594"}, "Contact": {"owner": "Sunpower", "contact": "Bennet Meyers", "contact_details": "bennet.meyers@nrel.gov", "comments": "Legacy ingest of Sunpower data from SLAC PVDB"}, "Mount": {}, "Inverters": {"Inverter 0": {"inverter_id": "30180", "name": "2000682875", "manufacturer": "Unknown", "model": "", "type": "", "quantity": "1", "serial_num": "", "comments": "PVDB_API_HID=2000682875", "time_interval": "L", "modules_per_string": "", "num_strings": ""}, "Inverter 1": {"inverter_id": "30181", "name": "0022F2002E48", "manufacturer": "Unknown", "model": "", "type": "", "quantity": "1", "serial_num": "", "comments": "PVDB_API_HID=0022F2002E48", "time_interval": "L", "modules_per_string": "", "num_strings": ""}}, "Modules": {}, "Meters": {}, "Other Instruments": {}, "Metrics": {"ac_current_inv_30181": {"metric_id": 160251, "sensor_name": "0022F2002E48_ac_current", "common_name": "AC current", "raw_units": "A", "units": "A", "calc_scale": 1.0, "calc_offset": 0.0, "calc_details": null, "aggregation_type": "avg", "source_type": "INVERTER", "source_id": 30181, "comments": "PVDB_API_HID=0022F2002E48", "offline": true}, "ac_frequency_inv_30181": {"metric_id": 185416, "sensor_name": "0022F2002E48_ac_frequency", "common_name": "AC frequency", "raw_units": "Hz", "units": "Hz", "calc_scale": 1.0, "calc_offset": 0.0, "calc_details": null, "aggregation_type": "avg", "source_type": "INVERTER", "source_id": 30181, "comments": "PVDB_API_HID=0022F2002E48", "offline": true}, "ac_power_inv_30181": {"metric_id": 160250, "sensor_name": "0022F2002E48_ac_power", "common_name": "AC power", "raw_units": "kW", "units": "kW", "calc_scale": 1.0, "calc_offset": 0.0, "calc_details": null, "aggregation_type": "avg", "source_type": "INVERTER", "source_id": 30181, "comments": "PVDB_API_HID=0022F2002E48", "offline": true}, "ac_voltage_inv_30181": {"metric_id": 160249, "sensor_name": "0022F2002E48_ac_voltage", "common_name": "AC voltage", "raw_units": "V", "units": "V", "calc_scale": 1.0, "calc_offset": 0.0, "calc_details": null, "aggregation_type": "avg", "source_type": "INVERTER", "source_id": 30181, "comments": "PVDB_API_HID=0022F2002E48", "offline": true}, "dc_current_inv_30181": {"metric_id": 160248, "sensor_name": "0022F2002E48_dc_current", "common_name": "DC current", "raw_units": "A", "units": "A", "calc_scale": 1.0, "calc_offset": 0.0, "calc_details": null, "aggregation_type": "avg", "source_type": "INVERTER", "source_id": 30181, "comments": "PVDB_API_HID=0022F2002E48", "offline": true}, "dc_power_inv_30181": {"metric_id": 160247, "sensor_name": "0022F2002E48_dc_power", "common_name": "DC power", "raw_units": "kW", "units": "kW", "calc_scale": 1.0, "calc_offset": 0.0, "calc_details": null, "aggregation_type": "avg", "source_type": "INVERTER", "source_id": 30181, "comments": "PVDB_API_HID=0022F2002E48", "offline": true}, "dc_voltage_inv_30181": {"metric_id": 160246, "sensor_name": "0022F2002E48_dc_voltage", "common_name": "DC voltage", "raw_units": "V", "units": "V", "calc_scale": 1.0, "calc_offset": 0.0, "calc_details": null, "aggregation_type": "avg", "source_type": "INVERTER", "source_id": 30181, "comments": "PVDB_API_HID=0022F2002E48", "offline": true}, "ac_energy_other_inv_30181": {"metric_id": 185413, "sensor_name": "0022F2002E48_energy_harvested_today", "common_name": "AC energy other", "raw_units": "kWh", "units": "kWh", "calc_scale": 1.0, "calc_offset": 0.0, "calc_details": null, "aggregation_type": "sum", "source_type": "INVERTER", "source_id": 30181, "comments": "PVDB_API_HID=0022F2002E48", "offline": true}, "ac_energy_cumulative_inv_30181": {"metric_id": 160245, "sensor_name": "0022F2002E48_energy_harvested_total", "common_name": "AC energy cumulative", "raw_units": "kWh", "units": "kWh", "calc_scale": 1.0, "calc_offset": 0.0, "calc_details": null, "aggregation_type": "avg", "source_type": "INVERTER", "source_id": 30181, "comments": "PVDB_API_HID=0022F2002E48", "offline": true}, "temperature_inverter_inv_30181": {"metric_id": 160244, "sensor_name": "0022F2002E48_heatsink_temp", "common_name": "Temperature inverter", "raw_units": "C", "units": "C", "calc_scale": 1.0, "calc_offset": 0.0, "calc_details": null, "aggregation_type": "avg", "source_type": "INVERTER", "source_id": 30181, "comments": "PVDB_API_HID=0022F2002E48", "offline": true}, "ac_current_inv_30180": {"metric_id": 160242, "sensor_name": "2000682875_ac_current", "common_name": "AC current", "raw_units": "A", "units": "A", "calc_scale": 1.0, "calc_offset": 0.0, "calc_details": null, "aggregation_type": "avg", "source_type": "INVERTER", "source_id": 30180, "comments": "PVDB_API_HID=2000682875", "offline": true}, "ac_frequency_inv_30180": {"metric_id": 185415, "sensor_name": "2000682875_ac_frequency", "common_name": "AC frequency", "raw_units": "Hz", "units": "Hz", "calc_scale": 1.0, "calc_offset": 0.0, "calc_details": null, "aggregation_type": "avg", "source_type": "INVERTER", "source_id": 30180, "comments": "PVDB_API_HID=2000682875", "offline": true}, "ac_power_inv_30180": {"metric_id": 160241, "sensor_name": "2000682875_ac_power", "common_name": "AC power", "raw_units": "kW", "units": "kW", "calc_scale": 1.0, "calc_offset": 0.0, "calc_details": null, "aggregation_type": "avg", "source_type": "INVERTER", "source_id": 30180, "comments": "PVDB_API_HID=2000682875", "offline": true}, "ac_voltage_inv_30180": {"metric_id": 160240, "sensor_name": "2000682875_ac_voltage", "common_name": "AC voltage", "raw_units": "V", "units": "V", "calc_scale": 1.0, "calc_offset": 0.0, "calc_details": null, "aggregation_type": "avg", "source_type": "INVERTER", "source_id": 30180, "comments": "PVDB_API_HID=2000682875", "offline": true}, "dc_current_inv_30180": {"metric_id": 160239, "sensor_name": "2000682875_dc_current", "common_name": "DC current", "raw_units": "A", "units": "A", "calc_scale": 1.0, "calc_offset": 0.0, "calc_details": null, "aggregation_type": "avg", "source_type": "INVERTER", "source_id": 30180, "comments": "PVDB_API_HID=2000682875", "offline": true}, "dc_power_inv_30180": {"metric_id": 160238, "sensor_name": "2000682875_dc_power", "common_name": "DC power", "raw_units": "kW", "units": "kW", "calc_scale": 1.0, "calc_offset": 0.0, "calc_details": null, "aggregation_type": "avg", "source_type": "INVERTER", "source_id": 30180, "comments": "PVDB_API_HID=2000682875", "offline": true}, "dc_voltage_inv_30180": {"metric_id": 160236, "sensor_name": "2000682875_dc_voltage", "common_name": "DC voltage", "raw_units": "V", "units": "V", "calc_scale": 1.0, "calc_offset": 0.0, "calc_details": null, "aggregation_type": "avg", "source_type": "INVERTER", "source_id": 30180, "comments": "PVDB_API_HID=2000682875", "offline": true}, "ac_energy_other_inv_30180": {"metric_id": 185414, "sensor_name": "2000682875_energy_harvested_today", "common_name": "AC energy other", "raw_units": "kWh", "units": "kWh", "calc_scale": 1.0, "calc_offset": 0.0, "calc_details": null, "aggregation_type": "sum", "source_type": "INVERTER", "source_id": 30180, "comments": "PVDB_API_HID=2000682875", "offline": true}, "ac_energy_cumulative_inv_30180": {"metric_id": 160237, "sensor_name": "2000682875_energy_harvested_total", "common_name": "AC energy cumulative", "raw_units": "kWh", "units": "kWh", "calc_scale": 1.0, "calc_offset": 0.0, "calc_details": null, "aggregation_type": "avg", "source_type": "INVERTER", "source_id": 30180, "comments": "PVDB_API_HID=2000682875", "offline": true}, "temperature_inverter_inv_30180": {"metric_id": 160243, "sensor_name": "2000682875_heatsink_temp", "common_name": "Temperature inverter", "raw_units": "C", "units": "C", "calc_scale": 1.0, "calc_offset": 0.0, "calc_details": null, "aggregation_type": "avg", "source_type": "INVERTER", "source_id": 30180, "comments": "PVDB_API_HID=2000682875", "offline": true}}}