{"System": {"system_id": 14524, "site_id": 7279, "name": "TABE01001626", "public_name": "PVDB_TABE01001626", "area": "", "power": "12.26", "started_on": "2013-12-31 00:00:00", "ended_on": "", "comments": "PVDB_SYSTEM_ID=TABE01001626", "public": "t", "access_id": 18, "grouping": "PVDB", "data_prize": "f", "timezone_code": "America/Los_Angeles"}, "Site": {"site_id": "7279", "name": "TABE01001626", "public_name": "PVDB_TABE01001626", "latitude": "33.78286", "longitude": "-117.80296", "elevation": "110.859756469727"}, "Contact": {"owner": "Sunpower", "contact": "Bennet Meyers", "contact_details": "bennet.meyers@nrel.gov", "comments": "Legacy ingest of Sunpower data from SLAC PVDB"}, "Mount": {}, "Inverters": {"Inverter 0": {"inverter_id": "30212", "name": "2002117407", "manufacturer": "Unknown", "model": "", "type": "", "quantity": "1", "serial_num": "", "comments": "PVDB_API_HID=2002117407", "time_interval": "L", "modules_per_string": "", "num_strings": ""}, "Inverter 1": {"inverter_id": "30213", "name": "2002117239", "manufacturer": "Unknown", "model": "", "type": "", "quantity": "1", "serial_num": "", "comments": "PVDB_API_HID=2002117239", "time_interval": "L", "modules_per_string": "", "num_strings": ""}, "Inverter 2": {"inverter_id": "30214", "name": "2002100137", "manufacturer": "Unknown", "model": "", "type": "", "quantity": "1", "serial_num": "", "comments": "PVDB_API_HID=2002100137", "time_interval": "L", "modules_per_string": "", "num_strings": ""}}, "Modules": {}, "Meters": {}, "Other Instruments": {}, "Metrics": {"ac_current_inv_30214": {"metric_id": 160508, "sensor_name": "2002100137_ac_curr", "common_name": "AC current", "raw_units": "A", "units": "A", "calc_scale": 1.0, "calc_offset": 0.0, "calc_details": null, "aggregation_type": "avg", "source_type": "INVERTER", "source_id": 30214, "comments": "PVDB_API_HID=2002100137", "offline": true}, "ac_power_inv_30214": {"metric_id": 160509, "sensor_name": "2002100137_ac_power", "common_name": "AC power", "raw_units": "kW", "units": "kW", "calc_scale": 1.0, "calc_offset": 0.0, "calc_details": null, "aggregation_type": "avg", "source_type": "INVERTER", "source_id": 30214, "comments": "PVDB_API_HID=2002100137", "offline": true}, "ac_voltage_inv_30214": {"metric_id": 160510, "sensor_name": "2002100137_ac_volt", "common_name": "AC voltage", "raw_units": "V", "units": "V", "calc_scale": 1.0, "calc_offset": 0.0, "calc_details": null, "aggregation_type": "avg", "source_type": "INVERTER", "source_id": 30214, "comments": "PVDB_API_HID=2002100137", "offline": true}, "dc_current_inv_30214": {"metric_id": 160512, "sensor_name": "2002100137_dc_curr", "common_name": "DC current", "raw_units": "A", "units": "A", "calc_scale": 1.0, "calc_offset": 0.0, "calc_details": null, "aggregation_type": "avg", "source_type": "INVERTER", "source_id": 30214, "comments": "PVDB_API_HID=2002100137", "offline": true}, "dc_power_inv_30214": {"metric_id": 160511, "sensor_name": "2002100137_dc_power", "common_name": "DC power", "raw_units": "kW", "units": "kW", "calc_scale": 1.0, "calc_offset": 0.0, "calc_details": null, "aggregation_type": "avg", "source_type": "INVERTER", "source_id": 30214, "comments": "PVDB_API_HID=2002100137", "offline": true}, "dc_voltage_inv_30214": {"metric_id": 160517, "sensor_name": "2002100137_dc_volt", "common_name": "DC voltage", "raw_units": "V", "units": "V", "calc_scale": 1.0, "calc_offset": 0.0, "calc_details": null, "aggregation_type": "avg", "source_type": "INVERTER", "source_id": 30214, "comments": "PVDB_API_HID=2002100137", "offline": true}, "ac_energy_inv_30214": {"metric_id": 185522, "sensor_name": "2002100137_energy_day", "common_name": "AC energy", "raw_units": "kWh", "units": "kWh", "calc_scale": 1.0, "calc_offset": 0.0, "calc_details": null, "aggregation_type": "sum", "source_type": "INVERTER", "source_id": 30214, "comments": "PVDB_API_HID=2002100137", "offline": true}, "ac_energy_cumulative_inv_30214": {"metric_id": 160513, "sensor_name": "2002100137_energy_total", "common_name": "AC energy cumulative", "raw_units": "kWh", "units": "kWh", "calc_scale": 1.0, "calc_offset": 0.0, "calc_details": null, "aggregation_type": "avg", "source_type": "INVERTER", "source_id": 30214, "comments": "PVDB_API_HID=2002100137", "offline": true}, "ac_frequency_inv_30214": {"metric_id": 185525, "sensor_name": "2002100137_freq", "common_name": "AC frequency", "raw_units": "Hz", "units": "Hz", "calc_scale": 1.0, "calc_offset": 0.0, "calc_details": null, "aggregation_type": "avg", "source_type": "INVERTER", "source_id": 30214, "comments": "PVDB_API_HID=2002100137", "offline": true}, "temperature_inverter_inv_30214": {"metric_id": 160514, "sensor_name": "2002100137_heatsink_temp", "common_name": "Temperature inverter", "raw_units": "C", "units": "C", "calc_scale": 1.0, "calc_offset": 0.0, "calc_details": null, "aggregation_type": "avg", "source_type": "INVERTER", "source_id": 30214, "comments": "PVDB_API_HID=2002100137", "offline": true}, "other_inv_30214": {"metric_id": 185519, "sensor_name": "2002100137_op_hrs_total", "common_name": "Other", "raw_units": "hr", "units": "hr", "calc_scale": 1.0, "calc_offset": 0.0, "calc_details": null, "aggregation_type": "sum", "source_type": "INVERTER", "source_id": 30214, "comments": "PVDB_API_HID=2002100137", "offline": true}, "ac_current_inv_30213": {"metric_id": 160515, "sensor_name": "2002117239_ac_curr", "common_name": "AC current", "raw_units": "A", "units": "A", "calc_scale": 1.0, "calc_offset": 0.0, "calc_details": null, "aggregation_type": "avg", "source_type": "INVERTER", "source_id": 30213, "comments": "PVDB_API_HID=2002117239", "offline": true}, "ac_power_inv_30213": {"metric_id": 160516, "sensor_name": "2002117239_ac_power", "common_name": "AC power", "raw_units": "kW", "units": "kW", "calc_scale": 1.0, "calc_offset": 0.0, "calc_details": null, "aggregation_type": "avg", "source_type": "INVERTER", "source_id": 30213, "comments": "PVDB_API_HID=2002117239", "offline": true}, "ac_voltage_inv_30213": {"metric_id": 160506, "sensor_name": "2002117239_ac_volt", "common_name": "AC voltage", "raw_units": "V", "units": "V", "calc_scale": 1.0, "calc_offset": 0.0, "calc_details": null, "aggregation_type": "avg", "source_type": "INVERTER", "source_id": 30213, "comments": "PVDB_API_HID=2002117239", "offline": true}, "dc_current_inv_30213": {"metric_id": 160507, "sensor_name": "2002117239_dc_curr", "common_name": "DC current", "raw_units": "A", "units": "A", "calc_scale": 1.0, "calc_offset": 0.0, "calc_details": null, "aggregation_type": "avg", "source_type": "INVERTER", "source_id": 30213, "comments": "PVDB_API_HID=2002117239", "offline": true}, "dc_power_inv_30213": {"metric_id": 160504, "sensor_name": "2002117239_dc_power", "common_name": "DC power", "raw_units": "kW", "units": "kW", "calc_scale": 1.0, "calc_offset": 0.0, "calc_details": null, "aggregation_type": "avg", "source_type": "INVERTER", "source_id": 30213, "comments": "PVDB_API_HID=2002117239", "offline": true}, "dc_voltage_inv_30213": {"metric_id": 160503, "sensor_name": "2002117239_dc_volt", "common_name": "DC voltage", "raw_units": "V", "units": "V", "calc_scale": 1.0, "calc_offset": 0.0, "calc_details": null, "aggregation_type": "avg", "source_type": "INVERTER", "source_id": 30213, "comments": "PVDB_API_HID=2002117239", "offline": true}, "ac_energy_inv_30213": {"metric_id": 185523, "sensor_name": "2002117239_energy_day", "common_name": "AC energy", "raw_units": "kWh", "units": "kWh", "calc_scale": 1.0, "calc_offset": 0.0, "calc_details": null, "aggregation_type": "sum", "source_type": "INVERTER", "source_id": 30213, "comments": "PVDB_API_HID=2002117239", "offline": true}, "ac_energy_cumulative_inv_30213": {"metric_id": 160502, "sensor_name": "2002117239_energy_total", "common_name": "AC energy cumulative", "raw_units": "kWh", "units": "kWh", "calc_scale": 1.0, "calc_offset": 0.0, "calc_details": null, "aggregation_type": "avg", "source_type": "INVERTER", "source_id": 30213, "comments": "PVDB_API_HID=2002117239", "offline": true}, "ac_frequency_inv_30213": {"metric_id": 185526, "sensor_name": "2002117239_freq", "common_name": "AC frequency", "raw_units": "Hz", "units": "Hz", "calc_scale": 1.0, "calc_offset": 0.0, "calc_details": null, "aggregation_type": "avg", "source_type": "INVERTER", "source_id": 30213, "comments": "PVDB_API_HID=2002117239", "offline": true}, "temperature_inverter_inv_30213": {"metric_id": 160501, "sensor_name": "2002117239_heatsink_temp", "common_name": "Temperature inverter", "raw_units": "C", "units": "C", "calc_scale": 1.0, "calc_offset": 0.0, "calc_details": null, "aggregation_type": "avg", "source_type": "INVERTER", "source_id": 30213, "comments": "PVDB_API_HID=2002117239", "offline": true}, "other_inv_30213": {"metric_id": 185518, "sensor_name": "2002117239_op_hrs_total", "common_name": "Other", "raw_units": "hr", "units": "hr", "calc_scale": 1.0, "calc_offset": 0.0, "calc_details": null, "aggregation_type": "sum", "source_type": "INVERTER", "source_id": 30213, "comments": "PVDB_API_HID=2002117239", "offline": true}, "ac_current_inv_30212": {"metric_id": 160505, "sensor_name": "2002117407_ac_curr", "common_name": "AC current", "raw_units": "A", "units": "A", "calc_scale": 1.0, "calc_offset": 0.0, "calc_details": null, "aggregation_type": "avg", "source_type": "INVERTER", "source_id": 30212, "comments": "PVDB_API_HID=2002117407", "offline": true}, "ac_power_inv_30212": {"metric_id": 160500, "sensor_name": "2002117407_ac_power", "common_name": "AC power", "raw_units": "kW", "units": "kW", "calc_scale": 1.0, "calc_offset": 0.0, "calc_details": null, "aggregation_type": "avg", "source_type": "INVERTER", "source_id": 30212, "comments": "PVDB_API_HID=2002117407", "offline": true}, "ac_voltage_inv_30212": {"metric_id": 160499, "sensor_name": "2002117407_ac_volt", "common_name": "AC voltage", "raw_units": "V", "units": "V", "calc_scale": 1.0, "calc_offset": 0.0, "calc_details": null, "aggregation_type": "avg", "source_type": "INVERTER", "source_id": 30212, "comments": "PVDB_API_HID=2002117407", "offline": true}, "dc_current_inv_30212": {"metric_id": 160498, "sensor_name": "2002117407_dc_curr", "common_name": "DC current", "raw_units": "A", "units": "A", "calc_scale": 1.0, "calc_offset": 0.0, "calc_details": null, "aggregation_type": "avg", "source_type": "INVERTER", "source_id": 30212, "comments": "PVDB_API_HID=2002117407", "offline": true}, "dc_power_inv_30212": {"metric_id": 160497, "sensor_name": "2002117407_dc_power", "common_name": "DC power", "raw_units": "kW", "units": "kW", "calc_scale": 1.0, "calc_offset": 0.0, "calc_details": null, "aggregation_type": "avg", "source_type": "INVERTER", "source_id": 30212, "comments": "PVDB_API_HID=2002117407", "offline": true}, "dc_voltage_inv_30212": {"metric_id": 160496, "sensor_name": "2002117407_dc_volt", "common_name": "DC voltage", "raw_units": "V", "units": "V", "calc_scale": 1.0, "calc_offset": 0.0, "calc_details": null, "aggregation_type": "avg", "source_type": "INVERTER", "source_id": 30212, "comments": "PVDB_API_HID=2002117407", "offline": true}, "ac_energy_inv_30212": {"metric_id": 185524, "sensor_name": "2002117407_energy_day", "common_name": "AC energy", "raw_units": "kWh", "units": "kWh", "calc_scale": 1.0, "calc_offset": 0.0, "calc_details": null, "aggregation_type": "sum", "source_type": "INVERTER", "source_id": 30212, "comments": "PVDB_API_HID=2002117407", "offline": true}, "ac_energy_cumulative_inv_30212": {"metric_id": 160495, "sensor_name": "2002117407_energy_total", "common_name": "AC energy cumulative", "raw_units": "kWh", "units": "kWh", "calc_scale": 1.0, "calc_offset": 0.0, "calc_details": null, "aggregation_type": "avg", "source_type": "INVERTER", "source_id": 30212, "comments": "PVDB_API_HID=2002117407", "offline": true}, "ac_frequency_inv_30212": {"metric_id": 185521, "sensor_name": "2002117407_freq", "common_name": "AC frequency", "raw_units": "Hz", "units": "Hz", "calc_scale": 1.0, "calc_offset": 0.0, "calc_details": null, "aggregation_type": "avg", "source_type": "INVERTER", "source_id": 30212, "comments": "PVDB_API_HID=2002117407", "offline": true}, "temperature_inverter_inv_30212": {"metric_id": 160494, "sensor_name": "2002117407_heatsink_temp", "common_name": "Temperature inverter", "raw_units": "C", "units": "C", "calc_scale": 1.0, "calc_offset": 0.0, "calc_details": null, "aggregation_type": "avg", "source_type": "INVERTER", "source_id": 30212, "comments": "PVDB_API_HID=2002117407", "offline": true}, "other_inv_30212": {"metric_id": 185520, "sensor_name": "2002117407_op_hrs_total", "common_name": "Other", "raw_units": "hr", "units": "hr", "calc_scale": 1.0, "calc_offset": 0.0, "calc_details": null, "aggregation_type": "sum", "source_type": "INVERTER", "source_id": 30212, "comments": "PVDB_API_HID=2002117407", "offline": true}}}