{"System": {"system_id": 14748, "site_id": 7694, "name": "TADBC1077995", "public_name": "PVDB_TADBC1077995", "area": "", "power": "", "started_on": "2015-03-18 00:00:00", "ended_on": "", "comments": "PVDB_SYSTEM_ID=TADBC1077995", "public": "t", "access_id": 18, "grouping": "PVDB", "data_prize": "f", "timezone_code": "America/Los_Angeles"}, "Site": {"site_id": "7694", "name": "TADBC1077995", "public_name": "PVDB_TADBC1077995", "latitude": "33.75564", "longitude": "-117.78714", "elevation": "104.228904724121"}, "Contact": {"owner": "Sunpower", "contact": "Bennet Meyers", "contact_details": "bennet.meyers@nrel.gov", "comments": "Legacy ingest of Sunpower data from SLAC PVDB"}, "Mount": {}, "Inverters": {"Inverter 0": {"inverter_id": "32555", "name": "839237902", "manufacturer": "Unknown", "model": "", "type": "", "quantity": "1", "serial_num": "", "comments": "PVDB_API_HID=839237902", "time_interval": "L", "modules_per_string": "", "num_strings": ""}, "Inverter 1": {"inverter_id": "32556", "name": "839216975", "manufacturer": "Unknown", "model": "", "type": "", "quantity": "1", "serial_num": "", "comments": "PVDB_API_HID=839216975", "time_interval": "L", "modules_per_string": "", "num_strings": ""}, "Inverter 2": {"inverter_id": "32557", "name": "839216977", "manufacturer": "Unknown", "model": "", "type": "", "quantity": "1", "serial_num": "", "comments": "PVDB_API_HID=839216977", "time_interval": "L", "modules_per_string": "", "num_strings": ""}, "Inverter 3": {"inverter_id": "32558", "name": "839201911", "manufacturer": "Unknown", "model": "", "type": "", "quantity": "1", "serial_num": "", "comments": "PVDB_API_HID=839201911", "time_interval": "L", "modules_per_string": "", "num_strings": ""}}, "Modules": {}, "Meters": {}, "Other Instruments": {}, "Metrics": {"ac_current_inv_32558": {"metric_id": 184833, "sensor_name": "839201911_ac_curr", "common_name": "AC current", "raw_units": "A", "units": "A", "calc_scale": 1.0, "calc_offset": 0.0, "calc_details": null, "aggregation_type": "avg", "source_type": "INVERTER", "source_id": 32558, "comments": "PVDB_API_HID=839201911", "offline": true}, "ac_power_inv_32558": {"metric_id": 184858, "sensor_name": "839201911_ac_power", "common_name": "AC power", "raw_units": "kW", "units": "kW", "calc_scale": 1.0, "calc_offset": 0.0, "calc_details": null, "aggregation_type": "avg", "source_type": "INVERTER", "source_id": 32558, "comments": "PVDB_API_HID=839201911", "offline": true}, "ac_voltage_inv_32558": {"metric_id": 184853, "sensor_name": "839201911_ac_volt", "common_name": "AC voltage", "raw_units": "V", "units": "V", "calc_scale": 1.0, "calc_offset": 0.0, "calc_details": null, "aggregation_type": "avg", "source_type": "INVERTER", "source_id": 32558, "comments": "PVDB_API_HID=839201911", "offline": true}, "dc_current_inv_32558": {"metric_id": 184843, "sensor_name": "839201911_dc_curr", "common_name": "DC current", "raw_units": "A", "units": "A", "calc_scale": 1.0, "calc_offset": 0.0, "calc_details": null, "aggregation_type": "avg", "source_type": "INVERTER", "source_id": 32558, "comments": "PVDB_API_HID=839201911", "offline": true}, "dc_power_inv_32558": {"metric_id": 184849, "sensor_name": "839201911_dc_power", "common_name": "DC power", "raw_units": "kW", "units": "kW", "calc_scale": 1.0, "calc_offset": 0.0, "calc_details": null, "aggregation_type": "avg", "source_type": "INVERTER", "source_id": 32558, "comments": "PVDB_API_HID=839201911", "offline": true}, "dc_voltage_inv_32558": {"metric_id": 184844, "sensor_name": "839201911_dc_volt", "common_name": "DC voltage", "raw_units": "V", "units": "V", "calc_scale": 1.0, "calc_offset": 0.0, "calc_details": null, "aggregation_type": "avg", "source_type": "INVERTER", "source_id": 32558, "comments": "PVDB_API_HID=839201911", "offline": true}, "ac_energy_inv_32558": {"metric_id": 185859, "sensor_name": "839201911_energy_day", "common_name": "AC energy", "raw_units": "kWh", "units": "kWh", "calc_scale": 1.0, "calc_offset": 0.0, "calc_details": null, "aggregation_type": "sum", "source_type": "INVERTER", "source_id": 32558, "comments": "PVDB_API_HID=839201911", "offline": true}, "ac_energy_cumulative_inv_32558": {"metric_id": 184836, "sensor_name": "839201911_energy_total", "common_name": "AC energy cumulative", "raw_units": "kWh", "units": "kWh", "calc_scale": 1.0, "calc_offset": 0.0, "calc_details": null, "aggregation_type": "avg", "source_type": "INVERTER", "source_id": 32558, "comments": "PVDB_API_HID=839201911", "offline": true}, "ac_frequency_inv_32558": {"metric_id": 185860, "sensor_name": "839201911_freq", "common_name": "AC frequency", "raw_units": "Hz", "units": "Hz", "calc_scale": 1.0, "calc_offset": 0.0, "calc_details": null, "aggregation_type": "avg", "source_type": "INVERTER", "source_id": 32558, "comments": "PVDB_API_HID=839201911", "offline": true}, "temperature_inverter_inv_32558": {"metric_id": 184831, "sensor_name": "839201911_heatsink_temp", "common_name": "Temperature inverter", "raw_units": "C", "units": "C", "calc_scale": 1.0, "calc_offset": 0.0, "calc_details": null, "aggregation_type": "avg", "source_type": "INVERTER", "source_id": 32558, "comments": "PVDB_API_HID=839201911", "offline": true}, "ac_power_other_inv_32558": {"metric_id": 185849, "sensor_name": "839201911_max_power_day", "common_name": "AC power other", "raw_units": "kW", "units": "kW", "calc_scale": 1.0, "calc_offset": 0.0, "calc_details": null, "aggregation_type": "max", "source_type": "INVERTER", "source_id": 32558, "comments": "PVDB_API_HID=839201911", "offline": true}, "other_inv_32558": {"metric_id": 185848, "sensor_name": "839201911_op_mins_day", "common_name": "Other", "raw_units": "min", "units": "min", "calc_scale": 1.0, "calc_offset": 0.0, "calc_details": null, "aggregation_type": "sum", "source_type": "INVERTER", "source_id": 32558, "comments": "PVDB_API_HID=839201911", "offline": true}, "ac_current_inv_32556": {"metric_id": 184834, "sensor_name": "839216975_ac_curr", "common_name": "AC current", "raw_units": "A", "units": "A", "calc_scale": 1.0, "calc_offset": 0.0, "calc_details": null, "aggregation_type": "avg", "source_type": "INVERTER", "source_id": 32556, "comments": "PVDB_API_HID=839216975", "offline": true}, "ac_power_inv_32556": {"metric_id": 184856, "sensor_name": "839216975_ac_power", "common_name": "AC power", "raw_units": "kW", "units": "kW", "calc_scale": 1.0, "calc_offset": 0.0, "calc_details": null, "aggregation_type": "avg", "source_type": "INVERTER", "source_id": 32556, "comments": "PVDB_API_HID=839216975", "offline": true}, "ac_voltage_inv_32556": {"metric_id": 184852, "sensor_name": "839216975_ac_volt", "common_name": "AC voltage", "raw_units": "V", "units": "V", "calc_scale": 1.0, "calc_offset": 0.0, "calc_details": null, "aggregation_type": "avg", "source_type": "INVERTER", "source_id": 32556, "comments": "PVDB_API_HID=839216975", "offline": true}, "dc_current_inv_32556": {"metric_id": 184842, "sensor_name": "839216975_dc_curr", "common_name": "DC current", "raw_units": "A", "units": "A", "calc_scale": 1.0, "calc_offset": 0.0, "calc_details": null, "aggregation_type": "avg", "source_type": "INVERTER", "source_id": 32556, "comments": "PVDB_API_HID=839216975", "offline": true}, "dc_power_inv_32556": {"metric_id": 184832, "sensor_name": "839216975_dc_power", "common_name": "DC power", "raw_units": "kW", "units": "kW", "calc_scale": 1.0, "calc_offset": 0.0, "calc_details": null, "aggregation_type": "avg", "source_type": "INVERTER", "source_id": 32556, "comments": "PVDB_API_HID=839216975", "offline": true}, "dc_voltage_inv_32556": {"metric_id": 184828, "sensor_name": "839216975_dc_volt", "common_name": "DC voltage", "raw_units": "V", "units": "V", "calc_scale": 1.0, "calc_offset": 0.0, "calc_details": null, "aggregation_type": "avg", "source_type": "INVERTER", "source_id": 32556, "comments": "PVDB_API_HID=839216975", "offline": true}, "ac_energy_inv_32556": {"metric_id": 185858, "sensor_name": "839216975_energy_day", "common_name": "AC energy", "raw_units": "kWh", "units": "kWh", "calc_scale": 1.0, "calc_offset": 0.0, "calc_details": null, "aggregation_type": "sum", "source_type": "INVERTER", "source_id": 32556, "comments": "PVDB_API_HID=839216975", "offline": true}, "ac_energy_cumulative_inv_32556": {"metric_id": 184837, "sensor_name": "839216975_energy_total", "common_name": "AC energy cumulative", "raw_units": "kWh", "units": "kWh", "calc_scale": 1.0, "calc_offset": 0.0, "calc_details": null, "aggregation_type": "avg", "source_type": "INVERTER", "source_id": 32556, "comments": "PVDB_API_HID=839216975", "offline": true}, "ac_frequency_inv_32556": {"metric_id": 185862, "sensor_name": "839216975_freq", "common_name": "AC frequency", "raw_units": "Hz", "units": "Hz", "calc_scale": 1.0, "calc_offset": 0.0, "calc_details": null, "aggregation_type": "avg", "source_type": "INVERTER", "source_id": 32556, "comments": "PVDB_API_HID=839216975", "offline": true}, "temperature_inverter_inv_32556": {"metric_id": 184830, "sensor_name": "839216975_heatsink_temp", "common_name": "Temperature inverter", "raw_units": "C", "units": "C", "calc_scale": 1.0, "calc_offset": 0.0, "calc_details": null, "aggregation_type": "avg", "source_type": "INVERTER", "source_id": 32556, "comments": "PVDB_API_HID=839216975", "offline": true}, "ac_power_other_inv_32556": {"metric_id": 185850, "sensor_name": "839216975_max_power_day", "common_name": "AC power other", "raw_units": "kW", "units": "kW", "calc_scale": 1.0, "calc_offset": 0.0, "calc_details": null, "aggregation_type": "max", "source_type": "INVERTER", "source_id": 32556, "comments": "PVDB_API_HID=839216975", "offline": true}, "other_inv_32556": {"metric_id": 185853, "sensor_name": "839216975_op_mins_day", "common_name": "Other", "raw_units": "min", "units": "min", "calc_scale": 1.0, "calc_offset": 0.0, "calc_details": null, "aggregation_type": "sum", "source_type": "INVERTER", "source_id": 32556, "comments": "PVDB_API_HID=839216975", "offline": true}, "ac_current_inv_32557": {"metric_id": 184835, "sensor_name": "839216977_ac_curr", "common_name": "AC current", "raw_units": "A", "units": "A", "calc_scale": 1.0, "calc_offset": 0.0, "calc_details": null, "aggregation_type": "avg", "source_type": "INVERTER", "source_id": 32557, "comments": "PVDB_API_HID=839216977", "offline": true}, "ac_power_inv_32557": {"metric_id": 184847, "sensor_name": "839216977_ac_power", "common_name": "AC power", "raw_units": "kW", "units": "kW", "calc_scale": 1.0, "calc_offset": 0.0, "calc_details": null, "aggregation_type": "avg", "source_type": "INVERTER", "source_id": 32557, "comments": "PVDB_API_HID=839216977", "offline": true}, "ac_voltage_inv_32557": {"metric_id": 184851, "sensor_name": "839216977_ac_volt", "common_name": "AC voltage", "raw_units": "V", "units": "V", "calc_scale": 1.0, "calc_offset": 0.0, "calc_details": null, "aggregation_type": "avg", "source_type": "INVERTER", "source_id": 32557, "comments": "PVDB_API_HID=839216977", "offline": true}, "dc_current_inv_32557": {"metric_id": 184841, "sensor_name": "839216977_dc_curr", "common_name": "DC current", "raw_units": "A", "units": "A", "calc_scale": 1.0, "calc_offset": 0.0, "calc_details": null, "aggregation_type": "avg", "source_type": "INVERTER", "source_id": 32557, "comments": "PVDB_API_HID=839216977", "offline": true}, "dc_power_inv_32557": {"metric_id": 184848, "sensor_name": "839216977_dc_power", "common_name": "DC power", "raw_units": "kW", "units": "kW", "calc_scale": 1.0, "calc_offset": 0.0, "calc_details": null, "aggregation_type": "avg", "source_type": "INVERTER", "source_id": 32557, "comments": "PVDB_API_HID=839216977", "offline": true}, "dc_voltage_inv_32557": {"metric_id": 184829, "sensor_name": "839216977_dc_volt", "common_name": "DC voltage", "raw_units": "V", "units": "V", "calc_scale": 1.0, "calc_offset": 0.0, "calc_details": null, "aggregation_type": "avg", "source_type": "INVERTER", "source_id": 32557, "comments": "PVDB_API_HID=839216977", "offline": true}, "ac_energy_inv_32557": {"metric_id": 185857, "sensor_name": "839216977_energy_day", "common_name": "AC energy", "raw_units": "kWh", "units": "kWh", "calc_scale": 1.0, "calc_offset": 0.0, "calc_details": null, "aggregation_type": "sum", "source_type": "INVERTER", "source_id": 32557, "comments": "PVDB_API_HID=839216977", "offline": true}, "ac_energy_cumulative_inv_32557": {"metric_id": 184838, "sensor_name": "839216977_energy_total", "common_name": "AC energy cumulative", "raw_units": "kWh", "units": "kWh", "calc_scale": 1.0, "calc_offset": 0.0, "calc_details": null, "aggregation_type": "avg", "source_type": "INVERTER", "source_id": 32557, "comments": "PVDB_API_HID=839216977", "offline": true}, "ac_frequency_inv_32557": {"metric_id": 185861, "sensor_name": "839216977_freq", "common_name": "AC frequency", "raw_units": "Hz", "units": "Hz", "calc_scale": 1.0, "calc_offset": 0.0, "calc_details": null, "aggregation_type": "avg", "source_type": "INVERTER", "source_id": 32557, "comments": "PVDB_API_HID=839216977", "offline": true}, "temperature_inverter_inv_32557": {"metric_id": 184846, "sensor_name": "839216977_heatsink_temp", "common_name": "Temperature inverter", "raw_units": "C", "units": "C", "calc_scale": 1.0, "calc_offset": 0.0, "calc_details": null, "aggregation_type": "avg", "source_type": "INVERTER", "source_id": 32557, "comments": "PVDB_API_HID=839216977", "offline": true}, "ac_power_other_inv_32557": {"metric_id": 185851, "sensor_name": "839216977_max_power_day", "common_name": "AC power other", "raw_units": "kW", "units": "kW", "calc_scale": 1.0, "calc_offset": 0.0, "calc_details": null, "aggregation_type": "max", "source_type": "INVERTER", "source_id": 32557, "comments": "PVDB_API_HID=839216977", "offline": true}, "other_inv_32557": {"metric_id": 185854, "sensor_name": "839216977_op_mins_day", "common_name": "Other", "raw_units": "min", "units": "min", "calc_scale": 1.0, "calc_offset": 0.0, "calc_details": null, "aggregation_type": "sum", "source_type": "INVERTER", "source_id": 32557, "comments": "PVDB_API_HID=839216977", "offline": true}, "ac_current_inv_32555": {"metric_id": 184845, "sensor_name": "839237902_ac_curr", "common_name": "AC current", "raw_units": "A", "units": "A", "calc_scale": 1.0, "calc_offset": 0.0, "calc_details": null, "aggregation_type": "avg", "source_type": "INVERTER", "source_id": 32555, "comments": "PVDB_API_HID=839237902", "offline": true}, "ac_power_inv_32555": {"metric_id": 184855, "sensor_name": "839237902_ac_power", "common_name": "AC power", "raw_units": "kW", "units": "kW", "calc_scale": 1.0, "calc_offset": 0.0, "calc_details": null, "aggregation_type": "avg", "source_type": "INVERTER", "source_id": 32555, "comments": "PVDB_API_HID=839237902", "offline": true}, "ac_voltage_inv_32555": {"metric_id": 184850, "sensor_name": "839237902_ac_volt", "common_name": "AC voltage", "raw_units": "V", "units": "V", "calc_scale": 1.0, "calc_offset": 0.0, "calc_details": null, "aggregation_type": "avg", "source_type": "INVERTER", "source_id": 32555, "comments": "PVDB_API_HID=839237902", "offline": true}, "dc_current_inv_32555": {"metric_id": 184840, "sensor_name": "839237902_dc_curr", "common_name": "DC current", "raw_units": "A", "units": "A", "calc_scale": 1.0, "calc_offset": 0.0, "calc_details": null, "aggregation_type": "avg", "source_type": "INVERTER", "source_id": 32555, "comments": "PVDB_API_HID=839237902", "offline": true}, "dc_power_inv_32555": {"metric_id": 184854, "sensor_name": "839237902_dc_power", "common_name": "DC power", "raw_units": "kW", "units": "kW", "calc_scale": 1.0, "calc_offset": 0.0, "calc_details": null, "aggregation_type": "avg", "source_type": "INVERTER", "source_id": 32555, "comments": "PVDB_API_HID=839237902", "offline": true}, "dc_voltage_inv_32555": {"metric_id": 184827, "sensor_name": "839237902_dc_volt", "common_name": "DC voltage", "raw_units": "V", "units": "V", "calc_scale": 1.0, "calc_offset": 0.0, "calc_details": null, "aggregation_type": "avg", "source_type": "INVERTER", "source_id": 32555, "comments": "PVDB_API_HID=839237902", "offline": true}, "ac_energy_inv_32555": {"metric_id": 185847, "sensor_name": "839237902_energy_day", "common_name": "AC energy", "raw_units": "kWh", "units": "kWh", "calc_scale": 1.0, "calc_offset": 0.0, "calc_details": null, "aggregation_type": "sum", "source_type": "INVERTER", "source_id": 32555, "comments": "PVDB_API_HID=839237902", "offline": true}, "ac_energy_cumulative_inv_32555": {"metric_id": 184839, "sensor_name": "839237902_energy_total", "common_name": "AC energy cumulative", "raw_units": "kWh", "units": "kWh", "calc_scale": 1.0, "calc_offset": 0.0, "calc_details": null, "aggregation_type": "avg", "source_type": "INVERTER", "source_id": 32555, "comments": "PVDB_API_HID=839237902", "offline": true}, "ac_frequency_inv_32555": {"metric_id": 185856, "sensor_name": "839237902_freq", "common_name": "AC frequency", "raw_units": "Hz", "units": "Hz", "calc_scale": 1.0, "calc_offset": 0.0, "calc_details": null, "aggregation_type": "avg", "source_type": "INVERTER", "source_id": 32555, "comments": "PVDB_API_HID=839237902", "offline": true}, "temperature_inverter_inv_32555": {"metric_id": 184857, "sensor_name": "839237902_heatsink_temp", "common_name": "Temperature inverter", "raw_units": "C", "units": "C", "calc_scale": 1.0, "calc_offset": 0.0, "calc_details": null, "aggregation_type": "avg", "source_type": "INVERTER", "source_id": 32555, "comments": "PVDB_API_HID=839237902", "offline": true}, "ac_power_other_inv_32555": {"metric_id": 185852, "sensor_name": "839237902_max_power_day", "common_name": "AC power other", "raw_units": "kW", "units": "kW", "calc_scale": 1.0, "calc_offset": 0.0, "calc_details": null, "aggregation_type": "max", "source_type": "INVERTER", "source_id": 32555, "comments": "PVDB_API_HID=839237902", "offline": true}, "other_inv_32555": {"metric_id": 185855, "sensor_name": "839237902_op_mins_day", "common_name": "Other", "raw_units": "min", "units": "min", "calc_scale": 1.0, "calc_offset": 0.0, "calc_details": null, "aggregation_type": "sum", "source_type": "INVERTER", "source_id": 32555, "comments": "PVDB_API_HID=839237902", "offline": true}}}